pylsl/__init__.py
pylsl/__version__.py
pylsl/info.py
pylsl/inlet.py
pylsl/outlet.py
pylsl/resolve.py
pylsl/util.py
pylsl/examples/GetTimeCorrection.py
pylsl/examples/HandleMetadata.py
pylsl/examples/PerformanceTest.py
pylsl/examples/README.md
pylsl/examples/ReceiveAndPlot.py
pylsl/examples/ReceiveData.py
pylsl/examples/ReceiveDataInChunks.py
pylsl/examples/ReceiveStringMarkers.py
pylsl/examples/SendData.py
pylsl/examples/SendDataAdvanced.py
pylsl/examples/SendStringMarkers.py
pylsl/examples/__init__.py
pylsl/lib/__init__.py
pylsl-1.18.1.dist-info/METADATA
pylsl-1.18.1.dist-info/WHEEL
pylsl-1.18.1.dist-info/top_level.txt
pylsl-1.18.1.dist-info/RECORD
