Metadata-Version: 2.4
Name: pylsl
Version: 1.18.1
Summary: Python library for importing XDF (Extensible Data Format)
Author-email: Christian Kothe <christian.kothe@intheon.io>, Chadwick Boulay <chadwick.boulay@gmail.com>
Project-URL: Repository, https://github.com/labstreaminglayer/pylsl
Project-URL: Issues, https://github.com/labstreaminglayer/pylsl/issues
Keywords: networking,LSL,Lab Streaming Layer,labstreaminglayer,data,acquisition,stream
Classifier: Development Status :: 5 - Production/Stable
Classifier: Intended Audience :: Developers
Classifier: Intended Audience :: Science/Research
Classifier: Topic :: System :: Networking
Classifier: Topic :: Scientific/Engineering
Classifier: License :: OSI Approved :: MIT License
Classifier: Operating System :: Microsoft :: Windows
Classifier: Operating System :: POSIX :: Linux
Classifier: Operating System :: MacOS
Classifier: Programming Language :: Python :: 3
Classifier: Programming Language :: Python :: 3.9
Classifier: Programming Language :: Python :: 3.10
Classifier: Programming Language :: Python :: 3.11
Classifier: Programming Language :: Python :: 3.12
Requires-Python: >=3.9
Requires-Dist: numpy<3,>=1.21
Provides-Extra: examples
Requires-Dist: pyqtgraph>=0.13.7; extra == "examples"
